fstop/__init__.py
fstop/core.py
fstop/cv.py
fstop/lexer.py
fstop/objects.py
fstop/operations.py
fstop/parser.py
f_stop-0.2.14.dist-info/LICENSE
f_stop-0.2.14.dist-info/METADATA
f_stop-0.2.14.dist-info/WHEEL
f_stop-0.2.14.dist-info/top_level.txt
f_stop-0.2.14.dist-info/zip-safe
f_stop-0.2.14.dist-info/RECORD
