Metadata-Version: 2.1
Name: f-stop
Version: 0.2.14
Summary: A basic scripting-lang for image-manipulation in python
Home-page: https://github.com/f-stop-lang/f-stop-rply/tree/iteration
Author: Tom-the-Bomb
License: MIT
Project-URL: Repository, https://github.com/f-stop-lang/f-stop-rply/tree/iteration
Project-URL: Issue tracker, https://github.com/f-stop-lang/f-stop-rply/issues
Platform: UNKNOWN
Classifier: License :: OSI Approved :: MIT License
Classifier: Intended Audience :: Developers
Classifier: Programming Language :: Python
Classifier: Natural Language :: English
Classifier: Programming Language :: Python :: 3.8
Classifier: Programming Language :: Python :: 3.9
Classifier: Topic :: Software Development :: Libraries
Requires-Python: >=3.8
Requires-Dist: Pillow
Requires-Dist: rply
Requires-Dist: opencv-python
